minot/__init__.py
minot/model.py
minot/model_admin.py
minot/model_modpar.py
minot/model_obs.py
minot/model_phys.py
minot/model_plots.py
minot/model_title.py
minot/model_tools.py
minot/ClusterTools/__init__.py
minot/ClusterTools/cluster_electron_emission.py
minot/ClusterTools/cluster_electron_loss.py
minot/ClusterTools/cluster_global.py
minot/ClusterTools/cluster_hadronic_emission_kafexhiu2014.py
minot/ClusterTools/cluster_hadronic_emission_kelner2006.py
minot/ClusterTools/cluster_profile.py
minot/ClusterTools/cluster_spectra.py
minot/ClusterTools/cluster_szspec.py
minot/ClusterTools/cluster_xspec.py
minot/ClusterTools/map_tools.py
minot/ClusterTools/plotting_style.py
minot-1.1.3.dist-info/LICENSE
minot-1.1.3.dist-info/METADATA
minot-1.1.3.dist-info/WHEEL
minot-1.1.3.dist-info/top_level.txt
minot-1.1.3.dist-info/RECORD
