Metadata-Version: 2.1
Name: minot
Version: 1.1.3
Summary: Python code to model the intra cluster medium thermal and non-thermal components and provide predictions for associated observables
Home-page: https://github.com/remi-adam/minot
Author: Remi Adam
Author-email: remi.adam@oca.eu
License: BSD
Platform: UNKNOWN
Classifier: Development Status :: 4 - Beta
Classifier: Intended Audience :: Science/Research
Classifier: Topic :: Scientific/Engineering :: Astronomy
Classifier: License :: OSI Approved :: BSD License
Classifier: Programming Language :: Python :: 2
Classifier: Programming Language :: Python :: 3
License-File: LICENSE
